CHANGES.rst
LICENSE.txt
MANIFEST.in
README.rst
dev-requirements.txt
requirements.txt
setup.py
version.py
Tardis_time.egg-info/PKG-INFO
Tardis_time.egg-info/SOURCES.txt
Tardis_time.egg-info/dependency_links.txt
Tardis_time.egg-info/requires.txt
Tardis_time.egg-info/top_level.txt
docs/contribution.rst
docs/index.rst
docs/install.rst
docs/interface.rst
docs/license.rst
docs/quickstart.rst
tardis/__init__.py
tardis/dates.py
tardis/exceptions.py
tardis/interface.py
tests/tardis_tests.py